EXPERIMENTATION/LAB_ACTIVITY_1/num3/old/combi_ckt.v
module combi_ckt (a, b, c, y);
 

    input a, b, c;
    output y;

    assign y = ( (!((a && c) || (b && c))) || (!(a && c)) );

endmodule

EXPERIMENTATION/LAB_ACTIVITY_1/num3/old/combi_ckt_tb.v
`include "combi_ckt.v"
module combi_ckt_tb;
    reg a, b, c;
    wire y;
 

    combi_ckt uut(a, b, c, y);
 
    initial begin
    $dumpfile("combi_ckt.vcd");
    $dumpvars(0, combi_ckt_tb);
        a = 0; b = 0; c = 0;  
        #3
        a = 0; b = 0; c = 1;  
        #3
        a = 0; b = 1; c = 0;  
        #3
        a = 0; b = 1; c = 1;  
        #3
        a = 1; b = 0; c = 0;  
        #3
        a = 1; b = 0; c = 1;  
        #3
        a = 1; b = 1; c = 0; 
        #3
        a = 1; b = 1; c = 1;  
        #3;
 
    end
endmodule

EXPERIMENTATION/LAB_ACTIVITY_1/num3/old/combi_ckt.vcd
$date
	Tue Oct 25 21:07:51 2022
$end
$version
	Icarus Verilog
$end
$timescale
	1s
$end
$scope module combi_ckt_tb $end
$var wire 1 ! y $end
$var reg 1 " a $end
$var reg 1 # b $end
$var reg 1 $ c $end
$scope module uut $end
$var wire 1 % a $end
$var wire 1 & b $end
$var wire 1 ' c $end
$var wire 1 ! y $end
$upscope $end
$upscope $end
$enddefinitions $end
#0
$dumpvars
0'
0&
0%
0$
0#
0"
1!
$end
#3
1$
1'
#6
0$
0'
1#
1&
#9
1$
1'
#12
0$
0'
0#
0&
1"
1%
#15
0!
1$
1'
#18
1!
0$
0'
1#
1&
#21
0!
1$
1'
