EXPERIMENTATION/LAB_ACTIVITY_1/num4/activity_num_four.v
module combi_circuit;

    reg A, B, C;
    wire Y;

    assign Y = ( (A && B) || ((!A) && B) || ((!B) && C) );

    initial begin
        $dumpfile("activity_num_four.vcd");
        $dumpvars(0, combi_circuit);
        
            A = 0; B = 0; C = 0;  
            #2
            A = 0; B = 0; C = 1;  
            #2
            A = 0; B = 1; C = 0;  
            #2
            A = 0; B = 1; C = 1;  
            #2
            A = 1; B = 0; C = 0;  
            #2
            A = 1; B = 0; C = 1;  
            #2
            A = 1; B = 1; C = 0;  
            #2
            A = 1; B = 1; C = 1;  
            #2;

    end


endmodule

//Keemchard Tamio

EXPERIMENTATION/LAB_ACTIVITY_1/num4/activity_num_four.vcd
$date
	Wed Oct 26 17:31:29 2022
$end
$version
	Icarus Verilog
$end
$timescale
	1s
$end
$scope module combi_circuit $end
$var wire 1 ! Y $end
$var reg 1 " A $end
$var reg 1 # B $end
$var reg 1 $ C $end
$upscope $end
$enddefinitions $end
#0
$dumpvars
0$
0#
0"
0!
$end
#2
1!
1$
#4
0$
1#
#6
1$
#8
0!
0$
0#
1"
#10
1!
1$
#12
0$
1#
#14
1$
