EXPERIMENTATION/num5/activity_num_five.v
module combi_circuit;

    reg A, B, C, D;
    wire Y;

    assign Y = ( ((!A)&&(B || ((!C)&&D))) || ((!A)&& C && D) );

    initial begin
        $dumpfile("activity_num_five.vcd");
        $dumpvars(0, combi_circuit);

            A = 0; B = 0; C = 0; D = 0;  
            #1
            A = 0; B = 0; C = 0; D = 1;   
            #1
            A = 0; B = 0; C = 1; D = 0;   
            #1
            A = 0; B = 0; C = 1; D = 1;   
            #1
            A = 0; B = 1; C = 0; D = 0;  
            #1
            A = 0; B = 1; C = 0; D = 1;   
            #1
            A = 0; B = 1; C = 1; D = 0;   
            #1
            A = 0; B = 1; C = 1; D = 1;   
            #1
            A = 1; B = 0; C = 0; D = 0;   
            #1
            A = 1; B = 0; C = 0; D = 1;  
            #1
            A = 1; B = 0; C = 1; D = 0;   
            #1
            A = 1; B = 0; C = 1; D = 1;   
            #1
            A = 1; B = 1; C = 0; D = 0;  
            #1
            A = 1; B = 1; C = 0; D = 1;   
            #1
            A = 1; B = 1; C = 1; D = 0;   
            #1
            A = 1; B = 1; C = 1; D = 1;   
            #1;

    end

endmodule

//Keemchard Tamio

EXPERIMENTATION/num5/activity_num_five.vcd
$date
	Wed Oct 26 17:35:23 2022
$end
$version
	Icarus Verilog
$end
$timescale
	1s
$end
$scope module combi_circuit $end
$var wire 1 ! Y $end
$var reg 1 " A $end
$var reg 1 # B $end
$var reg 1 $ C $end
$var reg 1 % D $end
$upscope $end
$enddefinitions $end
#0
$dumpvars
0%
0$
0#
0"
0!
$end
#1
1!
1%
#2
0!
0%
1$
#3
1!
1%
#4
0%
0$
1#
#5
1%
#6
0%
1$
#7
1%
#8
0!
0%
0$
0#
1"
#9
1%
#10
0%
1$
#11
1%
#12
0%
0$
1#
#13
1%
#14
0%
1$
#15
1%
