EXPERIMENTATION/num2/old/combi_ckt.v
module combi_ckt (a, b, c, d, y);
 

    input a, b, c, d;
    output y;

    assign y = (!( ( (a && b) || (a && c))  || ( (c || (!c)) && ((!d) || (a)) ) ));

endmodule

EXPERIMENTATION/num2/old/combi_ckt_tb.v
`include "combi_ckt.v"
module combi_ckt_tb;
    reg a, b, c, d;
    wire y;
 

    combi_ckt uut(a, b, c, d, y);
 
    initial begin
    $dumpfile("combi_ckt.vcd");
    $dumpvars(0, combi_ckt_tb);
        a = 0; b = 0; c = 0; d = 0;
        #1
        a = 0; b = 0; c = 0; d = 1;
        #1
        a = 0; b = 0; c = 1; d = 0;
        #1
        a = 0; b = 0; c = 1; d = 1;
        #1
        a = 0; b = 1; c = 0; d = 0;
        #1
        a = 0; b = 1; c = 0; d = 1;
        #1
        a = 0; b = 1; c = 1; d = 0;
        #1
        a = 0; b = 1; c = 1; d = 1;
        #1
        a = 1; b = 0; c = 0; d = 0;
        #1
        a = 1; b = 0; c = 0; d = 1;
        #1
        a = 1; b = 0; c = 1; d = 0;
        #1
        a = 1; b = 0; c = 1; d = 1;
        #1
        a = 1; b = 1; c = 0; d = 0;
        #1
        a = 1; b = 1; c = 0; d = 1;
        #1
        a = 1; b = 1; c = 1; d = 0;
        #1
        a = 1; b = 1; c = 1; d = 1;
        #1;
    end
endmodule

EXPERIMENTATION/num2/old/combi_ckt.vcd
$date
	Tue Oct 25 20:37:17 2022
$end
$version
	Icarus Verilog
$end
$timescale
	1s
$end
$scope module combi_ckt_tb $end
$var wire 1 ! y $end
$var reg 1 " a $end
$var reg 1 # b $end
$var reg 1 $ c $end
$var reg 1 % d $end
$scope module uut $end
$var wire 1 & a $end
$var wire 1 ' b $end
$var wire 1 ( c $end
$var wire 1 ) d $end
$var wire 1 ! y $end
$upscope $end
$upscope $end
$enddefinitions $end
#0
$dumpvars
0)
0(
0'
0&
0%
0$
0#
0"
0!
$end
#1
1!
1%
1)
#2
0!
0%
0)
1$
1(
#3
1!
1%
1)
#4
0!
0%
0)
0$
0(
1#
1'
#5
1!
1%
1)
#6
0!
0%
0)
1$
1(
#7
1!
1%
1)
#8
0!
0%
0)
0$
0(
0#
0'
1"
1&
#9
1%
1)
#10
0%
0)
1$
1(
#11
1%
1)
#12
0%
0)
0$
0(
1#
1'
#13
1%
1)
#14
0%
0)
1$
1(
#15
1%
1)
