EXPERIMENTATION/num2/activity_num_two.v
module combi_circuit;

    reg a, b, c, d;
    wire y;

    assign y = (!( ( (a && b) || (a && c))  || ( (c || (!c)) && ((!d) || (a)) ) ));

    initial begin

        $dumpfile("activity_num_two.vcd");
        $dumpvars(0, combi_circuit);
        
            a = 0; b = 0; c = 0; d = 0;
            #1
            a = 0; b = 0; c = 0; d = 1;
            #1
            a = 0; b = 0; c = 1; d = 0;
            #1
            a = 0; b = 0; c = 1; d = 1;
            #1
            a = 0; b = 1; c = 0; d = 0;
            #1
            a = 0; b = 1; c = 0; d = 1;
            #1
            a = 0; b = 1; c = 1; d = 0;
            #1
            a = 0; b = 1; c = 1; d = 1;
            #1
            a = 1; b = 0; c = 0; d = 0;
            #1
            a = 1; b = 0; c = 0; d = 1;
            #1
            a = 1; b = 0; c = 1; d = 0;
            #1
            a = 1; b = 0; c = 1; d = 1;
            #1
            a = 1; b = 1; c = 0; d = 0;
            #1
            a = 1; b = 1; c = 0; d = 1;
            #1
            a = 1; b = 1; c = 1; d = 0;
            #1
            a = 1; b = 1; c = 1; d = 1;
            #1;


    end

endmodule

//Keemchard Tamio

EXPERIMENTATION/num2/activity_num_two.vcd
$date
	Wed Oct 26 17:25:26 2022
$end
$version
	Icarus Verilog
$end
$timescale
	1s
$end
$scope module combi_circuit $end
$var wire 1 ! y $end
$var reg 1 " a $end
$var reg 1 # b $end
$var reg 1 $ c $end
$var reg 1 % d $end
$upscope $end
$enddefinitions $end
#0
$dumpvars
0%
0$
0#
0"
0!
$end
#1
1!
1%
#2
0!
0%
1$
#3
1!
1%
#4
0!
0%
0$
1#
#5
1!
1%
#6
0!
0%
1$
#7
1!
1%
#8
0!
0%
0$
0#
1"
#9
1%
#10
0%
1$
#11
1%
#12
0%
0$
1#
#13
1%
#14
0%
1$
#15
1%
