EXPERIMENTATION/LAB_ACTIVITY_1/num5/old/combi_ckt.v
module combi_ckt (A, B, C, D, Y);
 

    input A, B, C, D;
    output Y;

    assign Y = ( ((!A)&&(B || ((!C)&&D))) || ((!A)&& C && D) );

endmodule

EXPERIMENTATION/LAB_ACTIVITY_1/num5/old/combi_ckt_tb.v
`include "combi_ckt.v"
module combi_ckt_tb;
    reg A, B, C, D;
    wire Y;
 

    combi_ckt uut(A, B, C, D, Y);
 
    initial begin
    $dumpfile("combi_ckt.vcd");
    $dumpvars(0, combi_ckt_tb);
        A = 0; B = 0; C = 0; D = 0;  
        #1
        A = 0; B = 0; C = 0; D = 1;   
        #1
        A = 0; B = 0; C = 1; D = 0;   
        #1
        A = 0; B = 0; C = 1; D = 1;   
        #1
        A = 0; B = 1; C = 0; D = 0;  
        #1
        A = 0; B = 1; C = 0; D = 1;   
        #1
        A = 0; B = 1; C = 1; D = 0;   
        #1
        A = 0; B = 1; C = 1; D = 1;   
        #1
        A = 1; B = 0; C = 0; D = 0;   
        #1
        A = 1; B = 0; C = 0; D = 1;  
        #1
        A = 1; B = 0; C = 1; D = 0;   
        #1
        A = 1; B = 0; C = 1; D = 1;   
        #1
        A = 1; B = 1; C = 0; D = 0;  
        #1
        A = 1; B = 1; C = 0; D = 1;   
        #1
        A = 1; B = 1; C = 1; D = 0;   
        #1
        A = 1; B = 1; C = 1; D = 1;   
        #1;
 
    end
endmodule

EXPERIMENTATION/LAB_ACTIVITY_1/num5/old/combi_ckt.vcd
$date
	Tue Oct 25 21:45:32 2022
$end
$version
	Icarus Verilog
$end
$timescale
	1s
$end
$scope module combi_ckt_tb $end
$var wire 1 ! Y $end
$var reg 1 " A $end
$var reg 1 # B $end
$var reg 1 $ C $end
$var reg 1 % D $end
$scope module uut $end
$var wire 1 & A $end
$var wire 1 ' B $end
$var wire 1 ( C $end
$var wire 1 ) D $end
$var wire 1 ! Y $end
$upscope $end
$upscope $end
$enddefinitions $end
#0
$dumpvars
0)
0(
0'
0&
0%
0$
0#
0"
0!
$end
#1
1!
1%
1)
#2
0!
0%
0)
1$
1(
#3
1!
1%
1)
#4
0%
0)
0$
0(
1#
1'
#5
1%
1)
#6
0%
0)
1$
1(
#7
1%
1)
#8
0!
0%
0)
0$
0(
0#
0'
1"
1&
#9
1%
1)
#10
0%
0)
1$
1(
#11
1%
1)
#12
0%
0)
0$
0(
1#
1'
#13
1%
1)
#14
0%
0)
1$
1(
#15
1%
1)
